{
  "number": 5,
  "title": "Longest Palindromic Substring",
  "difficulty": "medium",
  "description": {
    "en": "Find longest palindrome substring",
    "zh-CN": "Find longest palindrome substring",
    "zh-TW": "Find longest palindrome substring",
    "ja": "Find longest palindrome substring",
    "es": "Find longest palindrome substring",
    "de": "Find longest palindrome substring",
    "fr": "Find longest palindrome substring"
  },
  "aplSolution": "LongestPalindrome ← {⊃⌽{⍵/⍨⍵≡¨⌽¨⍵}{⍵↑¨⊂⍵}⍨⍳≢⍵}",
  "explanation": {
    "en": "Generates all substrings, filters palindromes by comparing each with its reverse (⍵≡¨⌽¨⍵), reverses list (⌽) to get longest first, takes first element (⊃).",
    "zh-CN": "生成所有子串，通过比较每个子串与其反转 (⍵≡¨⌽¨⍵) 过滤回文，反转列表 (⌽) 使最长的在前，取第一个元素 (⊃)。",
    "zh-TW": "生成所有子串，通過比較每個子串與其反轉 (⍵≡¨⌽¨⍵) 過濾回文，反轉列表 (⌽) 使最長的在前，取第一個元素 (⊃)。",
    "ja": "検証済みの APL ソリューション",
    "es": "Solución APL verificada",
    "de": "Verifizierte APL-Lösung",
    "fr": "Solution APL vérifiée"
  },
  "timeComplexity": "O(n²)",
  "spaceComplexity": "O(1)",
  "verified": false,
  "testCases": []
}