{
  "number": 19,
  "title": "Remove Nth Node",
  "difficulty": "medium",
  "description": {
    "en": "Remove nth node from end",
    "zh-CN": "Remove nth node from end",
    "zh-TW": "Remove nth node from end",
    "ja": "Remove nth node from end",
    "es": "Remove nth node from end",
    "de": "Remove nth node from end",
    "fr": "Remove nth node from end"
  },
  "aplSolution": "RemoveNthFromEnd ← {((⍳≢⍵)~(≢⍵)-⍺)⌷⍵}",
  "explanation": {
    "en": "Remove nth from end",
    "zh-CN": "已驗證的 APL 解決方案",
    "zh-TW": "已驗證的 APL 解決方案",
    "ja": "検証済みの APL ソリューション",
    "es": "Solución APL verificada",
    "de": "Verifizierte APL-Lösung",
    "fr": "Solution APL vérifiée"
  },
  "timeComplexity": "O(n)",
  "spaceComplexity": "O(1)",
  "verified": false,
  "testCases": []
}