{
  "number": 118,
  "title": "Pascal's Triangle",
  "difficulty": "easy",
  "description": {
    "en": "Generate Pascal's triangle",
    "zh-CN": "Generate Pascal's triangle",
    "zh-TW": "Generate Pascal's triangle",
    "ja": "Generate Pascal's triangle",
    "es": "Generate Pascal's triangle",
    "de": "Generate Pascal's triangle",
    "fr": "Generate Pascal's triangle"
  },
  "aplSolution": "Generate ← {{0,⍵}+{⍵,0}}⍣⍵⊢1",
  "explanation": {
    "en": "Generates Pascal's triangle by repeatedly applying (0,⍵)+(⍵,0) to get next row.",
    "zh-CN": "已驗證的 APL 解決方案",
    "zh-TW": "已驗證的 APL 解決方案",
    "ja": "検証済みの APL ソリューション",
    "es": "Solución APL verificada",
    "de": "Verifizierte APL-Lösung",
    "fr": "Solution APL vérifiée"
  },
  "timeComplexity": "O(n²)",
  "spaceComplexity": "O(n²)",
  "verified": true,
  "verifiedDate": "2025-12-04",
  "testCases": []
}